{
  "updated_at": "2026-04-17T04:50:29.263Z",
  "global": {
    "total_market_cap_usd": 2626321559990.0244,
    "stablecoin_market_cap": 316206746037.21075,
    "defi_market_cap": 89510277671.45476
  },
  "coins": {
    "tether": {
      "name": "Tether",
      "symbol": "USDT",
      "image": "https://coin-images.coingecko.com/coins/images/325/large/Tether.png?1696501661",
      "market_cap": 185824252644,
      "market_cap_rank": 3,
      "current_price": 1,
      "price_change_percentage_24h": -0.00767,
      "total_volume": 78206991647,
      "circulating_supply": 185809000661.4175,
      "genesis_date": null,
      "age_years": null,
      "platforms": [
        "ethereum",
        "klay-token",
        "tezos",
        "tron",
        "solana",
        "near-protocol",
        "kava",
        "celo",
        "the-open-network",
        "aptos",
        "avalanche"
      ],
      "use_case": "payments"
    },
    "usd-coin": {
      "name": "USDC",
      "symbol": "USDC",
      "image": "https://coin-images.coingecko.com/coins/images/6319/large/USDC.png?1769615602",
      "market_cap": 78731666720,
      "market_cap_rank": 6,
      "current_price": 0.999831,
      "price_change_percentage_24h": 0.00788,
      "total_volume": 18149452547,
      "circulating_supply": 78745545724.75854,
      "genesis_date": null,
      "age_years": null,
      "platforms": [],
      "use_case": "payments"
    },
    "usds": {
      "name": "USDS",
      "symbol": "USDS",
      "image": "https://coin-images.coingecko.com/coins/images/39926/large/usds.webp?1726666683",
      "market_cap": 11347446316,
      "market_cap_rank": 12,
      "current_price": 0.999806,
      "price_change_percentage_24h": 0.0086,
      "total_volume": 55393283,
      "circulating_supply": 11349701833.63344,
      "genesis_date": null,
      "age_years": null,
      "platforms": [],
      "use_case": "defi"
    },
    "ethena-usde": {
      "name": "Ethena USDe",
      "symbol": "USDE",
      "image": "https://coin-images.coingecko.com/coins/images/33613/large/usde.png?1733810059",
      "market_cap": 5830691997,
      "market_cap_rank": 20,
      "current_price": 0.999683,
      "price_change_percentage_24h": -0.0431,
      "total_volume": 73777019,
      "circulating_supply": 5832814787.756157,
      "genesis_date": null,
      "age_years": null,
      "platforms": [],
      "use_case": "treasury"
    },
    "dai": {
      "name": "Dai",
      "symbol": "DAI",
      "image": "https://coin-images.coingecko.com/coins/images/9956/large/Badge_Dai.png?1696509996",
      "market_cap": 4342556029,
      "market_cap_rank": 25,
      "current_price": 0.999836,
      "price_change_percentage_24h": -0.00785,
      "total_volume": 17301490,
      "circulating_supply": 4343317916.271711,
      "genesis_date": null,
      "age_years": null,
      "platforms": [],
      "use_case": "defi"
    },
    "usd1-wlfi": {
      "name": "USD1",
      "symbol": "USD1",
      "image": "https://coin-images.coingecko.com/coins/images/54977/large/USD1_1000x1000_transparent.png?1749297002",
      "market_cap": 4128025895,
      "market_cap_rank": 27,
      "current_price": 1,
      "price_change_percentage_24h": 0.0308,
      "total_volume": 1315370094,
      "circulating_supply": 4127750544.391625,
      "genesis_date": null,
      "age_years": null,
      "platforms": [],
      "use_case": "payments"
    },
    "paypal-usd": {
      "name": "PayPal USD",
      "symbol": "PYUSD",
      "image": "https://coin-images.coingecko.com/coins/images/31212/large/PYUSD_Token_Logo_2x.png?1765987788",
      "market_cap": 4117243402,
      "market_cap_rank": 29,
      "current_price": 1,
      "price_change_percentage_24h": 0.00078,
      "total_volume": 95997930,
      "circulating_supply": 4117172315.412939,
      "genesis_date": null,
      "age_years": null,
      "platforms": [],
      "use_case": "payments"
    },
    "ripple-usd": {
      "name": "Ripple USD",
      "symbol": "RLUSD",
      "image": "https://coin-images.coingecko.com/coins/images/39651/large/RLUSD_200x200_%281%29.png?1727376633",
      "market_cap": 1480696782,
      "market_cap_rank": 57,
      "current_price": 0.999994,
      "price_change_percentage_24h": -0.01141,
      "total_volume": 157106423,
      "circulating_supply": 1480702011.407245,
      "genesis_date": null,
      "age_years": null,
      "platforms": [],
      "use_case": "payments"
    },
    "ondo-us-dollar-yield": {
      "name": "Ondo US Dollar Yield",
      "symbol": "USDY",
      "image": "https://coin-images.coingecko.com/coins/images/31700/large/usdy_%281%29.png?1696530524",
      "market_cap": 1371180903,
      "market_cap_rank": 60,
      "current_price": 1.13,
      "price_change_percentage_24h": 0.76658,
      "total_volume": 539997,
      "circulating_supply": 1214724967.504536,
      "genesis_date": null,
      "age_years": null,
      "platforms": [],
      "use_case": "treasury"
    },
    "usdtb": {
      "name": "USDtb",
      "symbol": "USDTB",
      "image": "https://coin-images.coingecko.com/coins/images/52804/large/76357aa8-4ef7-446c-bad3-a3f944eeec7a.jpeg?1758277468",
      "market_cap": 869082905,
      "market_cap_rank": 80,
      "current_price": 0.999792,
      "price_change_percentage_24h": -0.01636,
      "total_volume": 1056615,
      "circulating_supply": 869297988.5961826,
      "genesis_date": null,
      "age_years": null,
      "platforms": [],
      "use_case": "treasury"
    },
    "gho": {
      "name": "GHO",
      "symbol": "GHO",
      "image": "https://coin-images.coingecko.com/coins/images/30663/large/gho-token-logo.png?1720517092",
      "market_cap": 583720113,
      "market_cap_rank": 95,
      "current_price": 0.999561,
      "price_change_percentage_24h": -0.00314,
      "total_volume": 4615260,
      "circulating_supply": 584000000,
      "genesis_date": null,
      "age_years": null,
      "platforms": [],
      "use_case": "defi"
    },
    "ylds": {
      "name": "YLDS",
      "symbol": "YLDS",
      "image": "https://coin-images.coingecko.com/coins/images/66486/large/YLDS.png?1772560579",
      "market_cap": 574844084,
      "market_cap_rank": 96,
      "current_price": 0.999825,
      "price_change_percentage_24h": -0.00162,
      "total_volume": 16257802,
      "circulating_supply": 574944716.12,
      "genesis_date": null,
      "age_years": null,
      "platforms": [],
      "use_case": "treasury"
    },
    "usual-usd": {
      "name": "Usual USD",
      "symbol": "USD0",
      "image": "https://coin-images.coingecko.com/coins/images/38272/large/USD0LOGO.png?1716962811",
      "market_cap": 557532293,
      "market_cap_rank": 100,
      "current_price": 0.998176,
      "price_change_percentage_24h": -0.01006,
      "total_volume": 137117,
      "circulating_supply": 558557772.901634,
      "genesis_date": null,
      "age_years": null,
      "platforms": [],
      "use_case": "treasury"
    },
    "euro-coin": {
      "name": "EURC",
      "symbol": "EURC",
      "image": "https://coin-images.coingecko.com/coins/images/26045/large/EURC.png?1769615705",
      "market_cap": 425309797,
      "market_cap_rank": 114,
      "current_price": 1.18,
      "price_change_percentage_24h": -0.24407,
      "total_volume": 30900378,
      "circulating_supply": 361089641.5863731,
      "genesis_date": null,
      "age_years": null,
      "platforms": [],
      "use_case": "payments"
    },
    "first-digital-usd": {
      "name": "First Digital USD",
      "symbol": "FDUSD",
      "image": "https://coin-images.coingecko.com/coins/images/31079/large/FDUSD_icon_black.png?1731097953",
      "market_cap": 410768853,
      "market_cap_rank": 115,
      "current_price": 0.999808,
      "price_change_percentage_24h": 0.01559,
      "total_volume": 239602917,
      "circulating_supply": 410985192.71219,
      "genesis_date": null,
      "age_years": null,
      "platforms": [],
      "use_case": "payments"
    },
    "crvusd": {
      "name": "crvUSD",
      "symbol": "CRVUSD",
      "image": "https://coin-images.coingecko.com/coins/images/30118/large/crvusd.jpg?1746670973",
      "market_cap": 275791088,
      "market_cap_rank": 150,
      "current_price": 0.999684,
      "price_change_percentage_24h": -0.01709,
      "total_volume": 15743027,
      "circulating_supply": 275896184.5760332,
      "genesis_date": null,
      "age_years": null,
      "platforms": [],
      "use_case": "defi"
    },
    "frax": {
      "name": "Legacy Frax Dollar",
      "symbol": "FRAX",
      "image": "https://coin-images.coingecko.com/coins/images/13422/large/LFRAX.png?1751911193",
      "market_cap": 274057400,
      "market_cap_rank": 152,
      "current_price": 0.993238,
      "price_change_percentage_24h": -0.0995,
      "total_volume": 1114721,
      "circulating_supply": 275935184.0102677,
      "genesis_date": null,
      "age_years": null,
      "platforms": [],
      "use_case": "defi"
    },
    "stasis-eurs": {
      "name": "STASIS EURO",
      "symbol": "EURS",
      "image": "https://coin-images.coingecko.com/coins/images/5164/large/EURS_300x300.png?1696505680",
      "market_cap": 150360671,
      "market_cap_rank": 217,
      "current_price": 1.21,
      "price_change_percentage_24h": 0.08968,
      "total_volume": 786.65,
      "circulating_supply": 124125940,
      "genesis_date": null,
      "age_years": null,
      "platforms": [],
      "use_case": "payments"
    },
    "avant-usd": {
      "name": "Avant USD",
      "symbol": "AVUSD",
      "image": "https://coin-images.coingecko.com/coins/images/53527/large/token-avusd.png?1736579003",
      "market_cap": 127933894,
      "market_cap_rank": 243,
      "current_price": 0.99904,
      "price_change_percentage_24h": -0.08621,
      "total_volume": 30297,
      "circulating_supply": 128048558.5994445,
      "genesis_date": null,
      "age_years": null,
      "platforms": [],
      "use_case": "yield"
    },
    "resolv-usr": {
      "name": "Resolv USR",
      "symbol": "USR",
      "image": "https://coin-images.coingecko.com/coins/images/40008/large/USR_LOGO.png?1725222638",
      "market_cap": 18216944,
      "market_cap_rank": 901,
      "current_price": 0.130704,
      "price_change_percentage_24h": -13.09831,
      "total_volume": 21709,
      "circulating_supply": 139375333.7425654,
      "genesis_date": null,
      "age_years": null,
      "platforms": [],
      "use_case": "yield"
    },
    "falcon-finance": {
      "name": "Falcon USD",
      "symbol": "USDF",
      "image": "https://coin-images.coingecko.com/coins/images/54558/large/ff_200_X_200.png?1740741076",
      "market_cap": 1785716573,
      "market_cap_rank": 48,
      "current_price": 0.997846,
      "price_change_percentage_24h": 0.00731,
      "total_volume": 830982,
      "circulating_supply": 1789686283.753387,
      "genesis_date": null,
      "age_years": null,
      "platforms": [],
      "use_case": "yield"
    }
  }
}