{
  "updated_at": "2026-03-29T04:38:42.340Z",
  "global": {
    "total_market_cap_usd": 2381981707528.693,
    "stablecoin_market_cap": 309407814093.3129,
    "defi_market_cap": 79175969207.17422
  },
  "coins": {
    "tether": {
      "name": "Tether",
      "symbol": "USDT",
      "image": "https://coin-images.coingecko.com/coins/images/325/large/Tether.png?1696501661",
      "market_cap": 184076675651,
      "market_cap_rank": 3,
      "current_price": 0.999229,
      "price_change_percentage_24h": -0.00705,
      "total_volume": 38063428422,
      "circulating_supply": 184216554250.0974,
      "genesis_date": null,
      "age_years": null,
      "platforms": [
        "ethereum",
        "klay-token",
        "tezos",
        "tron",
        "solana",
        "near-protocol",
        "kava",
        "celo",
        "the-open-network",
        "aptos",
        "avalanche"
      ],
      "use_case": "payments"
    },
    "usd-coin": {
      "name": "USDC",
      "symbol": "USDC",
      "image": "https://coin-images.coingecko.com/coins/images/6319/large/USDC.png?1769615602",
      "market_cap": 77738789976,
      "market_cap_rank": 6,
      "current_price": 0.999746,
      "price_change_percentage_24h": 0.00202,
      "total_volume": 2625760621,
      "circulating_supply": 77758371191.2946,
      "genesis_date": null,
      "age_years": null,
      "platforms": [],
      "use_case": "payments"
    },
    "usds": {
      "name": "USDS",
      "symbol": "USDS",
      "image": "https://coin-images.coingecko.com/coins/images/39926/large/usds.webp?1726666683",
      "market_cap": 11478049363,
      "market_cap_rank": 11,
      "current_price": 0.999718,
      "price_change_percentage_24h": -0.01473,
      "total_volume": 25877486,
      "circulating_supply": 11481486805.07527,
      "genesis_date": null,
      "age_years": null,
      "platforms": [],
      "use_case": "defi"
    },
    "ethena-usde": {
      "name": "Ethena USDe",
      "symbol": "USDE",
      "image": "https://coin-images.coingecko.com/coins/images/33613/large/usde.png?1733810059",
      "market_cap": 5883246424,
      "market_cap_rank": 20,
      "current_price": 0.998978,
      "price_change_percentage_24h": -0.00839,
      "total_volume": 49742816,
      "circulating_supply": 5889454324.983891,
      "genesis_date": null,
      "age_years": null,
      "platforms": [],
      "use_case": "treasury"
    },
    "usd1-wlfi": {
      "name": "USD1",
      "symbol": "USD1",
      "image": "https://coin-images.coingecko.com/coins/images/54977/large/USD1_1000x1000_transparent.png?1749297002",
      "market_cap": 4395058930,
      "market_cap_rank": 22,
      "current_price": 0.999465,
      "price_change_percentage_24h": -0.00461,
      "total_volume": 601346832,
      "circulating_supply": 4396859954.173367,
      "genesis_date": null,
      "age_years": null,
      "platforms": [],
      "use_case": "payments"
    },
    "dai": {
      "name": "Dai",
      "symbol": "DAI",
      "image": "https://coin-images.coingecko.com/coins/images/9956/large/Badge_Dai.png?1696509996",
      "market_cap": 4297445097,
      "market_cap_rank": 23,
      "current_price": 0.999904,
      "price_change_percentage_24h": 0.00911,
      "total_volume": 392771928,
      "circulating_supply": 4297884226.760109,
      "genesis_date": null,
      "age_years": null,
      "platforms": [],
      "use_case": "defi"
    },
    "paypal-usd": {
      "name": "PayPal USD",
      "symbol": "PYUSD",
      "image": "https://coin-images.coingecko.com/coins/images/31212/large/PYUSD_Token_Logo_2x.png?1765987788",
      "market_cap": 3868202097,
      "market_cap_rank": 27,
      "current_price": 0.999812,
      "price_change_percentage_24h": 0.00871,
      "total_volume": 56123687,
      "circulating_supply": 3868930561.906864,
      "genesis_date": null,
      "age_years": null,
      "platforms": [],
      "use_case": "payments"
    },
    "ripple-usd": {
      "name": "Ripple USD",
      "symbol": "RLUSD",
      "image": "https://coin-images.coingecko.com/coins/images/39651/large/RLUSD_200x200_%281%29.png?1727376633",
      "market_cap": 1410314182,
      "market_cap_rank": 53,
      "current_price": 0.99981,
      "price_change_percentage_24h": -0.01784,
      "total_volume": 66256313,
      "circulating_supply": 1410355492.647286,
      "genesis_date": null,
      "age_years": null,
      "platforms": [],
      "use_case": "payments"
    },
    "ondo-us-dollar-yield": {
      "name": "Ondo US Dollar Yield",
      "symbol": "USDY",
      "image": "https://coin-images.coingecko.com/coins/images/31700/large/usdy_%281%29.png?1696530524",
      "market_cap": 1308565264,
      "market_cap_rank": 58,
      "current_price": 1.12,
      "price_change_percentage_24h": -0.33874,
      "total_volume": 848222,
      "circulating_supply": 1168481023.784602,
      "genesis_date": null,
      "age_years": null,
      "platforms": [],
      "use_case": "treasury"
    },
    "usdtb": {
      "name": "USDtb",
      "symbol": "USDTB",
      "image": "https://coin-images.coingecko.com/coins/images/52804/large/76357aa8-4ef7-446c-bad3-a3f944eeec7a.jpeg?1758277468",
      "market_cap": 877521155,
      "market_cap_rank": 71,
      "current_price": 0.999717,
      "price_change_percentage_24h": 0.05672,
      "total_volume": 1814773,
      "circulating_supply": 878092001.1061826,
      "genesis_date": null,
      "age_years": null,
      "platforms": [],
      "use_case": "treasury"
    },
    "ylds": {
      "name": "YLDS",
      "symbol": "YLDS",
      "image": "https://coin-images.coingecko.com/coins/images/66486/large/YLDS.png?1772560579",
      "market_cap": 592278258,
      "market_cap_rank": 88,
      "current_price": 0.999754,
      "price_change_percentage_24h": -0.02415,
      "total_volume": 2648446,
      "circulating_supply": 592421440.97,
      "genesis_date": null,
      "age_years": null,
      "platforms": [],
      "use_case": "treasury"
    },
    "gho": {
      "name": "GHO",
      "symbol": "GHO",
      "image": "https://coin-images.coingecko.com/coins/images/30663/large/gho-token-logo.png?1720517092",
      "market_cap": 583364014,
      "market_cap_rank": 89,
      "current_price": 0.998927,
      "price_change_percentage_24h": -0.0116,
      "total_volume": 849837,
      "circulating_supply": 584000000,
      "genesis_date": null,
      "age_years": null,
      "platforms": [],
      "use_case": "defi"
    },
    "usual-usd": {
      "name": "Usual USD",
      "symbol": "USD0",
      "image": "https://coin-images.coingecko.com/coins/images/38272/large/USD0LOGO.png?1716962811",
      "market_cap": 560677543,
      "market_cap_rank": 91,
      "current_price": 0.998649,
      "price_change_percentage_24h": -0.03494,
      "total_volume": 32105,
      "circulating_supply": 561435898.9031192,
      "genesis_date": null,
      "age_years": null,
      "platforms": [],
      "use_case": "treasury"
    },
    "euro-coin": {
      "name": "EURC",
      "symbol": "EURC",
      "image": "https://coin-images.coingecko.com/coins/images/26045/large/EURC.png?1769615705",
      "market_cap": 422155828,
      "market_cap_rank": 105,
      "current_price": 1.15,
      "price_change_percentage_24h": -0.05582,
      "total_volume": 12254496,
      "circulating_supply": 367436971.3505951,
      "genesis_date": null,
      "age_years": null,
      "platforms": [],
      "use_case": "payments"
    },
    "first-digital-usd": {
      "name": "First Digital USD",
      "symbol": "FDUSD",
      "image": "https://coin-images.coingecko.com/coins/images/31079/large/FDUSD_icon_black.png?1731097953",
      "market_cap": 398056390,
      "market_cap_rank": 110,
      "current_price": 0.998473,
      "price_change_percentage_24h": 0.00091,
      "total_volume": 24134963,
      "circulating_supply": 398629867.732202,
      "genesis_date": null,
      "age_years": null,
      "platforms": [],
      "use_case": "payments"
    },
    "frax": {
      "name": "Legacy Frax Dollar",
      "symbol": "FRAX",
      "image": "https://coin-images.coingecko.com/coins/images/13422/large/LFRAX.png?1751911193",
      "market_cap": 275168542,
      "market_cap_rank": 133,
      "current_price": 0.997362,
      "price_change_percentage_24h": 0.77299,
      "total_volume": 3693514,
      "circulating_supply": 275935184.0102677,
      "genesis_date": null,
      "age_years": null,
      "platforms": [],
      "use_case": "defi"
    },
    "crvusd": {
      "name": "crvUSD",
      "symbol": "CRVUSD",
      "image": "https://coin-images.coingecko.com/coins/images/30118/large/crvusd.jpg?1746670973",
      "market_cap": 263586627,
      "market_cap_rank": 138,
      "current_price": 0.997825,
      "price_change_percentage_24h": 0.0527,
      "total_volume": 1089201,
      "circulating_supply": 264163383.4597815,
      "genesis_date": null,
      "age_years": null,
      "platforms": [],
      "use_case": "defi"
    },
    "stasis-eurs": {
      "name": "STASIS EURO",
      "symbol": "EURS",
      "image": "https://coin-images.coingecko.com/coins/images/5164/large/EURS_300x300.png?1696505680",
      "market_cap": 152693173,
      "market_cap_rank": 199,
      "current_price": 1.23,
      "price_change_percentage_24h": 0.50584,
      "total_volume": 25082,
      "circulating_supply": 124125940,
      "genesis_date": null,
      "age_years": null,
      "platforms": [],
      "use_case": "payments"
    },
    "avant-usd": {
      "name": "Avant USD",
      "symbol": "AVUSD",
      "image": "https://coin-images.coingecko.com/coins/images/53527/large/token-avusd.png?1736579003",
      "market_cap": 127785355,
      "market_cap_rank": 224,
      "current_price": 0.999313,
      "price_change_percentage_24h": 0.02065,
      "total_volume": 213796,
      "circulating_supply": 127873166.2635261,
      "genesis_date": null,
      "age_years": null,
      "platforms": [],
      "use_case": "yield"
    },
    "resolv-usr": {
      "name": "Resolv USR",
      "symbol": "USR",
      "image": "https://coin-images.coingecko.com/coins/images/40008/large/USR_LOGO.png?1725222638",
      "market_cap": 28607634,
      "market_cap_rank": 643,
      "current_price": 0.162356,
      "price_change_percentage_24h": -3.29589,
      "total_volume": 12584.4,
      "circulating_supply": 176202716.1058388,
      "genesis_date": null,
      "age_years": null,
      "platforms": [],
      "use_case": "yield"
    },
    "falcon-finance": {
      "name": "Falcon USD",
      "symbol": "USDF",
      "image": "https://coin-images.coingecko.com/coins/images/54558/large/ff_200_X_200.png?1740741076",
      "market_cap": 1745905807,
      "market_cap_rank": 47,
      "current_price": 0.997431,
      "price_change_percentage_24h": -0.02537,
      "total_volume": 526396,
      "circulating_supply": 1750577869.143359,
      "genesis_date": null,
      "age_years": null,
      "platforms": [],
      "use_case": "yield"
    }
  }
}